robot_poete/__init__.py
robot_poete/robotPoete.py
robot_poete-0.1.0.dist-info/LICENSE
robot_poete-0.1.0.dist-info/METADATA
robot_poete-0.1.0.dist-info/WHEEL
robot_poete-0.1.0.dist-info/top_level.txt
robot_poete-0.1.0.dist-info/RECORD
