Metadata-Version: 2.1
Name: robot-poete
Version: 0.1.0
Summary: Le robot poète
Home-page: https://github.com/profelec/robot_poete
Author: Yoann VARENNE
Author-email: internetdesobjets69@gmail.com
License: UNKNOWN
Platform: UNKNOWN
Classifier: Programming Language :: Python :: 3
Classifier: License :: OSI Approved :: MIT License
Classifier: Operating System :: OS Independent
Requires-Python: >=3.6
